sms_hub_api/__init__.py
sms_hub_api/client.py
sms_hub_api/exceptions.py
sms_hub_api/types/__init__.py
sms_hub_api/types/activation.py
sms_hub_api/types/country.py
sms_hub_api/types/service.py
sms_hub_api/types/utils.py
sms_hub_api-0.1.5.dist-info/METADATA
sms_hub_api-0.1.5.dist-info/WHEEL
sms_hub_api-0.1.5.dist-info/top_level.txt
sms_hub_api-0.1.5.dist-info/RECORD
