Metadata-Version: 2.1
Name: sms-hub-api
Version: 0.1.5
Summary: UNKNOWN
Home-page: UNKNOWN
Author: daveusa31
License: UNKNOWN
Project-URL: Source, https://github.com/daveusa31/sms_hub_api
Platform: UNKNOWN
Classifier: Development Status :: 5 - Production/Stable
Classifier: Intended Audience :: Developers
Classifier: Natural Language :: Russian
Classifier: Programming Language :: Python
Classifier: Programming Language :: Python :: 3.6
Classifier: Programming Language :: Python :: 3.7
Classifier: Programming Language :: Python :: 3.8
Requires-Python: >=3.6
Requires-Dist: aiohttp (>=3.6.0)
